Workbook

Sheet T123
A1: T1 | H1: T3
A2: DTN Boat Company 2024 Sales Budget | H2: DTN Boat Company 2024 Direct Materials Budget
B3: Q1 | C3: Q2 | D3: Q3 | E3: Q4 | F3: Total | H3: Wood | I3: Q1 | J3: Q2 | K3: Q3 | L3: Q4 | M3: Total
A4: Sales volume | B4: 20 | C4: 40 | D4: 30 | E4: 10 | F4: 100 | H4: Production volume | I4: =B18 -> 30 | J4: =C18 -> 35 | K4: =D18 -> 20 | L4: =E18 -> 20 | M4: =F18 -> 105
A5: Price | B5: 10000 | C5: =B5 -> 10000 | D5: =C5 -> 10000 | E5: =D5 -> 10000 | H5: Standard feet per boat (100 feet) | I5: =100 -> 100 | J5: =100 -> 100 | K5: =100 -> 100 | L5: =100 -> 100
A6: Revenue earned | B6: =B4*B5 -> 200000 | C6: =C4*C5 -> 400000 | D6: =D4*D5 -> 300000 | E6: =E4*E5 -> 100000 | F6: =SUM(B6:E6) -> 1000000 | H6: Wood needed in production | I6: =I4*I5 -> 3000 | J6: =J4*J5 -> 3500 | K6: =K4*K5 -> 2000 | L6: =L4*L5 -> 2000 | M6: =SUM(I6:L6) -> 10500
A7: Received in current quarter *80% | B7: =B6*80% -> 160000 | C7: =C6*80% -> 320000 | D7: =D6*80% -> 240000 | E7: =E6*80% -> 80000 | F7: =SUM(B7:E7) -> 800000 | H7: Desired ending inventory | I7: =30%*J6 -> 1050 | J7: =30%*K6 -> 600 | K7: =30%*L6 -> 600 | L7: =30%*30*100 -> 900 | M7: =SUM(I7:L7) -> 3150
A8: Prior revenue collected | B8: 60000 | C8: =B6-B7 -> 40000 | D8: =C6-C7 -> 80000 | E8: =D6-D7 -> 60000 | F8: =SUM(B8:E8) -> 240000 | H8: Total wood need | I8: =I6+I7 -> 4050 | J8: =J6+J7 -> 4100 | K8: =K6+K7 -> 2600 | L8: =L6+L7 -> 2900 | M8: =SUM(I8:L8) -> 13650
A9: Collections from customers | B9: =B7+B8 -> 220000 | C9: =C7+C8 -> 360000 | D9: =D7+D8 -> 320000 | E9: =E7+E8 -> 140000 | F9: =SUM(B9:E9) -> 1040000 | H9: Less beginning inventory | I9: =J7 -> 600 | J9: =I7 -> 1050 | K9: =J7 -> 600 | L9: =K7 -> 600 | M9: =SUM(I9:L9) -> 2850
H10: Total wood purchase | I10: =I8-I9 -> 3450 | J10: =J8-J9 -> 3050 | K10: =K8-K9 -> 2000 | L10: =L8-L9 -> 2300 | M10: =SUM(I10:L10) -> 10800
A11: T2 | H11: Standard purchase price | I11: 10 | J11: 10 | K11: 10 | L11: 10
A12: DTN Boat Company 2024 Production Budget | H12: Total wood purchases | I12: =I10*I11 -> 34500 | J12: =J10*J11 -> 30500 | K12: =K10*K11 -> 20000 | L12: =L10*L11 -> 23000 | M12: =SUM(I12:L12) -> 108000
B13: Q1 | C13: Q2 | D13: Q3 | E13: Q4 | F13: Total | H13: Fiberglass | I13: Q1 | J13: Q2 | K13: Q3 | L13: Q4 | M13: Total
A14: Sales volume | B14: =B4 -> 20 | C14: =C4 -> 40 | D14: =D4 -> 30 | E14: =E4 -> 10 | F14: =F4 -> 100 | H14: Production volume | I14: =B18 -> 30 | J14: =C18 -> 35 | K14: =D18 -> 20 | L14: =E18 -> 20 | M14: =F18 -> 105
A15: Desired ending inventory*50% next Quarter | B15: =50%*C14 -> 20 | C15: =50%*D14 -> 15 | D15: =50%*E14 -> 5 | E15: 15 | F15: =SUM(B15:E15) -> 55 | H15: Standard feet per boat | I15: 40 | J15: 40 | K15: 40 | L15: 40
A16: Total boats needs | B16: =B14+B15 -> 40 | C16: =C14+C15 -> 55 | D16: =D14+D15 -> 35 | E16: =E14+E15 -> 25 | F16: =F14+F15 -> 155 | H16: Fiberglass needed in production | I16: =I14*I15 -> 1200 | J16: =J14*J15 -> 1400 | K16: =K14*K15 -> 800 | L16: =L14*L15 -> 800 | M16: =SUM(I16:L16) -> 4200
A17: Less beginning inventory | B17: 10 | C17: =B15 -> 20 | D17: =C15 -> 15 | E17: =D15 -> 5 | F17: =SUM(B17:E17) -> 50 | H17: Desired ending inventory | I17: =50%*J16 -> 700 | J17: =50%*K16 -> 400 | K17: =50%*L16 -> 400 | L17: =50%*30*40 -> 600 | M17: =SUM(I17:L17) -> 2100
A18: Total boats to produce | B18: =B16-B17 -> 30 | C18: =C16-C17 -> 35 | D18: =D16-D17 -> 20 | E18: =E16-E17 -> 20 | F18: =SUM(B18:E18) -> 105 | H18: Total fiberglass need | I18: =I16+I17 -> 1900 | J18: =J16+J17 -> 1800 | K18: =K16+K17 -> 1200 | L18: =L16+L17 -> 1400 | M18: =SUM(I18:L18) -> 6300
H19: Less beginning inventory | I19: 400 | J19: =I17 -> 700 | K19: =J17 -> 400 | L19: =K17 -> 400 | M19: =SUM(I19:L19) -> 1900
H20: Total fiberglass purchase | I20: =I18-I19 -> 1500 | J20: =J18-J19 -> 1100 | K20: =K18-K19 -> 800 | L20: =L18-L19 -> 1000 | M20: =SUM(I20:L20) -> 4400
H21: Standard purchase price | I21: 5 | J21: 5 | K21: 5 | L21: 5
H22: Total fiberglass purchases | I22: =I20*I21 -> 7500 | J22: =J20*J21 -> 5500 | K22: =K20*K21 -> 4000 | L22: =L20*L21 -> 5000 | M22: =SUM(I22:L22) -> 22000
I23: Q1 | J23: Q2 | K23: Q3 | L23: Q4 | M23: Total
H24: Total materials purchases | I24: =I12+I22 -> 42000 | J24: =J12+J22 -> 36000 | K24: =K12+K22 -> 24000 | L24: =L12+L22 -> 28000 | M24: =M12+M22 -> 130000
H25: Paid in current quarter | I25: 0.75 | J25: 0.75 | K25: 0.75 | L25: 0.75
H26: Current purchase payments | I26: =I24*I25 -> 31500 | J26: =J24*J25 -> 27000 | K26: =K24*K25 -> 18000 | L26: =L24*L25 -> 21000 | M26: =SUM(I26:L26) -> 97500
H27: Prior purchase payments | I27: 10000 | J27: =I24*25% -> 10500 | K27: =J24*25% -> 9000 | L27: =K24*25% -> 6000 | M27: =SUM(I27:L27) -> 35500
H28: Payments to suppliers | I28: =I26+I27 -> 41500 | J28: =J26+J27 -> 37500 | K28: =K26+K27 -> 27000 | L28: =L26+L27 -> 27000 | M28: =SUM(I28:L28) -> 133000

Sheet T456
A1: T4 | I1: T6
A2: DTN Boat Company 2024 Direct Labor Budget | I2: DTN Boat Company 2024 Budgeted Product Cost Sheet
B3: Q1 | C3: Q2 | D3: Q3 | E3: Q4 | F3: Total | J3: $ | K3: Total
A4: Production volume | B4: ='T123'!B18 -> 30 | C4: ='T123'!C18 -> 35 | D4: ='T123'!D18 -> 20 | E4: ='T123'!E18 -> 20 | F4: =SUM(B4:E4) -> 105 | I4: Direct materials cost per boat | K4: =K5+K6 -> 1200
A5: Standard hours per boat | B5: 80 | C5: 80 | D5: 80 | E5: 80 | I5: - Wood | J5: 10 | K5: =10*100 -> 1000
A6: Budgeted labor hours | B6: =B4*B5 -> 2400 | C6: =C4*C5 -> 2800 | D6: =D4*D5 -> 1600 | E6: =E4*E5 -> 1600 | F6: =SUM(B6:E6) -> 8400 | I6: - Fiberglass | J6: 5 | K6: =5*40 -> 200
A7: Standard wage rate per hour | B7: 20 | C7: 20 | D7: 20 | E7: 20 | I7: Direct labor cost per boat | J7: 20 | K7: =20*80 -> 1600
A8: Direct labor cost | B8: =B6*B7 -> 48000 | C8: =C6*C7 -> 56000 | D8: =D6*D7 -> 32000 | E8: =E6*E7 -> 32000 | F8: =SUM(B8:E8) -> 168000 | I8: Variable MOH cost per boat | J8: 7.5 | K8: =J8*80 -> 600
I9: Total variable cost per boat | J9: =SUM(J5:J8) -> 42.5 | K9: =J9*80 -> 3400
A10: T5 | I10: Total fixed MOH | K10: =G24 -> 168000
A11: DTN Boat Company 2024 Manufacturing Overhead Budget | I11: Divided by production volume | K11: ='T123'!F18 -> 105
A12: Variable MOH costs | C12: Q1 | D12: Q2 | E12: Q3 | F12: Q4 | G12: Total | I12: Fixed MOH cost allocated per boat | K12: =K10/K11 -> 1600
A13: Total labor hour | C13: =B6 -> 2400 | D13: =C6 -> 2800 | E13: =D6 -> 1600 | F13: =E6 -> 1600 | G13: =F6 -> 8400 | I13: Total production cost per boat | K13: =K9+K12 -> 5000
A14: Variable MOH rates per hour: | B14: $
A15: Indirect materials | B15: 1.5 | C15: =C13*$B$15 -> 3600 | D15: =D13*$B$15 -> 4200 | E15: =E13*$B$15 -> 2400 | F15: =F13*$B$15 -> 2400 | G15: =SUM(C15:F15) -> 12600
A16: Indirect labor | B16: 5 | C16: =C13*$B$16 -> 12000 | D16: =D13*$B$16 -> 14000 | E16: =E13*$B$16 -> 8000 | F16: =F13*$B$16 -> 8000 | G16: =SUM(C16:F16) -> 42000
A17: Utilities | B17: 1 | C17: =C13*$B$17 -> 2400 | D17: =D13*$B$17 -> 2800 | E17: =E13*$B$17 -> 1600 | F17: =F13*$B$17 -> 1600 | G17: =SUM(C17:F17) -> 8400
A18: Total variable MOH costs | C18: =SUM(C15:C17) -> 18000 | D18: =SUM(D15:D17) -> 21000 | E18: =SUM(E15:E17) -> 12000 | F18: =SUM(F15:F17) -> 12000 | G18: =SUM(C18:F18) -> 63000
A19: Fixed MOH cost per quarter | C19: Q1 | D19: Q2 | E19: Q3 | F19: Q4 | G19: Total
A20: Property tax | B20: 2000 | C20: 2000 | D20: 2000 | E20: 2000 | F20: 2000 | G20: =SUM(C20:F20) -> 8000
A21: Insurance | B21: 1000 | C21: 1000 | D21: 1000 | E21: 1000 | F21: 1000 | G21: =SUM(C21:F21) -> 4000
A22: Depreciation – plant | B22: 15000 | C22: 15000 | D22: 15000 | E22: 15000 | F22: 15000 | G22: =SUM(C22:F22) -> 60000
A23: Supervisor’s salaries | B23: 24000 | C23: 24000 | D23: 24000 | E23: 24000 | F23: 24000 | G23: =SUM(C23:F23) -> 96000
A24: Total fixed MOH costs | C24: =SUM(C20:C23) -> 42000 | D24: =SUM(D20:D23) -> 42000 | E24: =SUM(E20:E23) -> 42000 | F24: =SUM(F20:F23) -> 42000 | G24: =SUM(C24:F24) -> 168000
A25: Total | C25: Q1 | D25: Q2 | E25: Q3 | F25: Q4 | G25: Total
A26: Total MOH costs | C26: =C18+C24 -> 60000 | D26: =D18+D24 -> 63000 | E26: =E18+E24 -> 54000 | F26: =F18+F24 -> 54000 | G26: =SUM(B26:F26) -> 231000
A27: Less depreciation | C27: =C22 -> 15000 | D27: =D22 -> 15000 | E27: =E22 -> 15000 | F27: =F22 -> 15000 | G27: =SUM(B27:F27) -> 60000
A28: Total MOH payments | C28: =C26-C27 -> 45000 | D28: =D26-D27 -> 48000 | E28: =E26-E27 -> 39000 | F28: =F26-F27 -> 39000 | G28: =G26-G27 -> 171000

Sheet T78
A1: T7 | I1: T8
A2: DTN Boat Company 2024 Selling and Administrative (S&A) Expense Budget | I2: DTN Boat Company 2024 Cash Budget
A3: Variable S&A expenses | C3: Q1 | D3: Q2 | E3: Q3 | F3: Q4 | G3: Total | J3: Q1 | K3: Q2 | L3: Q3 | M3: Q4 | N3: Total
A4: Sales volume | C4: ='T123'!B4 -> 20 | D4: ='T123'!C4 -> 40 | E4: ='T123'!D4 -> 30 | F4: ='T123'!E4 -> 10 | G4: ='T123'!F4 -> 100 | I4: Receipts:
A5: Variable expense per boat sold: | B5: $ | I5: - Collections from customers | J5: ='T123'!B9 -> 220000 | K5: ='T123'!C9 -> 360000 | L5: ='T123'!D9 -> 320000 | M5: ='T123'!E9 -> 140000 | N5: ='T123'!F9 -> 1040000
A6: - Delivery expense | B6: =50000/100 -> 500 | C6: =C4*B6 -> 10000 | D6: =D4*B6 -> 20000 | E6: =E4*B6 -> 15000 | F6: =F4*B6 -> 5000 | G6: =SUM(C6:F6) -> 50000 | I6: Payments:
A7: - Sales commissions | B7: =10000*15% -> 1500 | C7: =C4*B7 -> 30000 | D7: =D4*B7 -> 60000 | E7: =E4*B7 -> 45000 | F7: =F4*B7 -> 15000 | G7: =SUM(C7:F7) -> 150000 | I7: - Direct materials | J7: ='T123'!I28 -> 41500 | K7: ='T123'!J28 -> 37500 | L7: ='T123'!K28 -> 27000 | M7: ='T123'!L28 -> 27000 | N7: ='T123'!M28 -> 133000
A8: Total variable S&A expenses | C8: =C6+C7 -> 40000 | D8: =D6+D7 -> 80000 | E8: =E6+E7 -> 60000 | F8: =F6+F7 -> 20000 | G8: =SUM(C8:F8) -> 200000 | I8: - Direct labor | J8: ='T456'!B8 -> 48000 | K8: ='T456'!C8 -> 56000 | L8: ='T456'!D8 -> 32000 | M8: ='T456'!E8 -> 32000 | N8: ='T456'!F8 -> 168000
A9: Fixed S&A expenses per quarter | B9: $ | C9: Q1 | D9: Q2 | E9: Q3 | F9: Q4 | G9: Total | I9: - Manufacturing Overhead | J9: ='T456'!C28 -> 45000 | K9: ='T456'!D28 -> 48000 | L9: ='T456'!E28 -> 39000 | M9: ='T456'!F28 -> 39000 | N9: ='T456'!G28 -> 171000
A10: Executives’ salaries | B10: 34000 | C10: 34000 | D10: 34000 | E10: 34000 | F10: 34000 | G10: =SUM(C10:F10) -> 136000 | I10: - Selling and Administrative expenses | J10: =C18 -> 86500 | K10: =D18 -> 126500 | L10: =E18 -> 106500 | M10: =F18 -> 66500 | N10: =G18 -> 386000
A11: Depreciation expense | B11: 5000 | C11: 5000 | D11: 5000 | E11: 5000 | F11: 5000 | G11: =SUM(C11:F11) -> 20000 | I11: - Income tax payment for 2023 | J11: 96000 | N11: =SUM(J11:M11) -> 96000
A12: Advertising expense | B12: 10000 | C12: 10000 | D12: 10000 | E12: 10000 | F12: 10000 | G12: =SUM(C12:F12) -> 40000 | I12: - Interest payment | K12: =60000*2.5% -> 1500 | N12: =SUM(J12:M12) -> 1500
A13: Miscellaneous expense | B13: 2500 | C13: 2500 | D13: 2500 | E13: 2500 | F13: 2500 | G13: =SUM(C13:F13) -> 10000 | I13: - Dividends | L13: 30000 | N13: =SUM(J13:M13) -> 30000
A14: Total fixed S&A expenses | C14: =SUM(C10:C13) -> 51500 | D14: =SUM(D10:D13) -> 51500 | E14: =SUM(E10:E13) -> 51500 | F14: =SUM(F10:F13) -> 51500 | G14: =SUM(G10:G13) -> 206000 | I14: - Equipment purchase | M14: 100000 | N14: =SUM(J14:M14) -> 100000
A15: Total | C15: Q1 | D15: Q2 | E15: Q3 | F15: Q4 | G15: Total | I15: Total payments | J15: =SUM(J7:J14) -> 317000 | K15: =SUM(K7:K14) -> 269500 | L15: =SUM(L7:L14) -> 234500 | M15: =SUM(M7:M14) -> 264500 | N15: =SUM(J15:M15) -> 1085500
A16: Total S&A expenses | C16: =C8+C14 -> 91500 | D16: =D8+D14 -> 131500 | E16: =E8+E14 -> 111500 | F16: =F8+F14 -> 71500 | G16: =G8+G14 -> 406000 | I16: Financing:
A17: Less depreciation | C17: =C11 -> 5000 | D17: =D11 -> 5000 | E17: =E11 -> 5000 | F17: =F11 -> 5000 | G17: =G11 -> 20000 | I17: - Beginning cash balance | J17: 137000 | K17: 100000 | L17: =K20-60000 -> 130500 | M17: =L20 -> 216000
A18: Total S&A payments | C18: =C16-C17 -> 86500 | D18: =D16-D17 -> 126500 | E18: =E16-E17 -> 106500 | F18: =F16-F17 -> 66500 | G18: =G16-G17 -> 386000 | I18: - Total receipts | J18: =J5 -> 220000 | K18: =K5 -> 360000 | L18: =L5 -> 320000 | M18: =M5 -> 140000 | N18: =N5 -> 1040000
I19: - Total payments | J19: =-J15 -> -317000 | K19: =-K15 -> -269500 | L19: =-L15 -> -234500 | M19: =-M15 -> -264500 | N19: =-N15 -> -1085500
I20: Cash available | J20: 40000 | K20: =SUM(K17:K19) -> 190500 | L20: =SUM(L17:L19) -> 216000 | M20: =SUM(M17:M19) -> 91500
I21: - Minimum cash balance desired | J21: 100000 | K21: 100000 | L21: 100000 | M21: 100000 | N21: =SUM(J21:M21) -> 400000
I22: - Cash excess (deficiency) | J22: =J20-J21 -> -60000 | K22: =K20-K21 -> 90500 | L22: =L20-L21 -> 116000 | M22: =M20-M21 -> -8500
I23: - Borrowings | J23: =-J22 -> 60000
I24: - Repayments of principle | K24: =J23 -> 60000
I25: Total financing inflows (outflows) | J25: =J23 -> 60000 | K25: =-K24 -> -60000 | M25: =8500 -> 8500
I26: Ending cash balance | J26: =K17 -> 100000 | K26: =L17 -> 130500 | L26: =M17 -> 216000 | M26: =100000 -> 100000

Sheet T910
A1: T9 | D1: T10
A2: DTN Boat Company Budgeted Cost of Goods Sold For the year Ended December 31, 2024 | D2: DTN Boat Company Budgeted Income Statement For the year Ended December 31, 2024
A3: Direct materials purchases | B3: ='T123'!M24 -> 130000 | D3: Sales revenue | E3: ='T123'!F6 -> 1000000
A4: Direct materials beginning inventory | B4: =8000 -> 8000 | D4: Cost of goods sold | E4: =B12 -> 500000
A5: Less direct materials ending inventory | B5: ='T123'!L7*10+'T123'!L17*5 -> 12000 | D5: - Gross margin | E5: =E3-E4 -> 500000
A6: Direct materials costs in production | B6: =B3+B4-B5 -> 126000 | D6: Selling and Administrative expense | E6: ='T78'!G16 -> 406000
A7: Direct labor costs in production | B7: ='T456'!F8 -> 168000 | D7: - Operating income | E7: =E5-E6 -> 94000
A8: MOH costs in production | B8: ='T456'!G26 -> 231000 | D8: Interest expense | E8: ='T78'!K12 -> 1500
A9: - Cost of goods manufactured | B9: =B6+B7+B8 -> 525000 | D9: Net income before tax | E9: =E7-E8 -> 92500
A10: Finished goods beginning inventory | B10: =50000 -> 50000 | D10: Income taxes (40%) | E10: =E9*40% -> 37000
A11: Less finish goods ending inventory | B11: =15*'T456'!K13 -> 75000 | D11: Net income after tax | E11: =E9-E10 -> 55500
A12: - Cost of goods sold | B12: =B9+B10-B11 -> 500000

Sheet T1112
A1: T11 | E1: T12
A2: DTN Boat Company Budgeted Balance Sheet December 31,2024 | E2: DTN Boat Company Budgeted Income Statement For the year Ended December 31, 2024
A3: Assets | E3: Cash flow from operating activities:
A4: Current assets: | E4: Net income | F4: ='T910'!E11 -> 55500
A5: Cash | B5: ='T78'!M26 -> 100000 | E5: Adjustment:
A6: Accounts receivable | B6: =20000 -> 20000 | E6: - Depreciation | F6: ='T78'!G11+'T456'!G22 -> 80000
A7: Direct materials inventory1 | B7: ='T910'!B5 -> 12000 | E7: - Accounts receivable increase (decrease) | F7: =60000-B6 -> 40000
A8: Finish goods inventory2 | B8: ='T910'!B11 -> 75000 | C8: =SUM(B5:B8) -> 207000 | E8: - Direct materials inventory increase (decrease) | F8: =8000-12000 -> -4000
A9: Long-term assets: | E9: - Finished goods inventory increase (decrease) | F9: =50000-B8 -> -25000
A10: Land | B10: =231500 -> 231500 | E10: - Account payable increase (decrease) | F10: =-(10000-B16) -> -3000
A11: Building and equipment | B11: =1500000+'T78'!M14 -> 1600000 | E11: - Income taxes payable increase (decrease) | F11: =-(96000-B17) -> -59000
A12: Less acumulated depreciation | B12: =120000+'T456'!G22+'T78'!G11 -> 200000 | C12: =B10+B11-B12 -> 1631500 | E12: Net cash provided by operating activities | G12: =SUM(F4:F11) -> 84500
A13: Total assets | C13: =C8+C12 -> 1838500
A14: Liabilites and Stockholder’s Equity | E14: Cash flow from investment activities
A15: Current liabilities: | E15: - Purchase of equipment | F15: =-'T78'!M14 -> -100000
A16: Account payable3 | B16: ='T123'!L24*25% -> 7000 | E16: Net cash used in investment activities | G16: =F15 -> -100000
A17: Income taxes payable3 | B17: ='T910'!E10 -> 37000
A18: Short-term loan payable | B18: ='T78'!M25 -> 8500 | C18: =B16+B17+B18 -> 52500 | E18: Cash flow from financing activities
A19: Stockholder’s equity: | E19: - Cash obtained from borrowing | F19: =60000+8500 -> 68500
A20: Common stock, $5 par | B20: =1000000 -> 1000000 | E20: - Payment of dividends | F20: =-30000 -> -30000
A21: Paid-in captial in excess of par | B21: =250000 -> 250000 | E21: - Repay of borowing | F21: =-60000 -> -60000
A22: Retained earnings | B22: =510500+'T910'!E11-'T78'!L13 -> 536000 | C22: =SUM(B20:B22) -> 1786000 | E22: Net cash used in financing activities: | G22: =F19+F20+F21 -> -21500
A23: Total liabilities and stockholder’s equity | C23: =C18+C22 -> 1838500 | E23: - Net increase (decrease) in cash | G23: =G12+G16+G22 -> -37000
E24: Beginning cash balance | G24: =137000 -> 137000
E25: Ending cash balance | G25: =G23+G24 -> 100000
